src/__init__.py
src/publish.py
src/subscribe.py
events_sdk-0.2.dist-info/METADATA
events_sdk-0.2.dist-info/WHEEL
events_sdk-0.2.dist-info/top_level.txt
events_sdk-0.2.dist-info/RECORD
